[
  {
    "inputs": [
      {
        "internalType": "address",
        "name": "bookkeeperAddr",
        "type": "address"
      }
    ],
    "stateMutability": "nonpayable",
    "type": "constructor"
  },
  {
    "anonymous": false,
    "inputs": [
      {
        "indexed": false,
        "internalType": "address",
        "name": "previousController",
        "type": "address"
      },
      {
        "indexed": false,
        "internalType": "address",
        "name": "newController",
        "type": "address"
      }
    ],
    "name": "ControlTransferred",
    "type": "event"
  },
  {
    "anonymous": false,
    "inputs": [
      {
        "indexed": false,
        "internalType": "uint8",
        "name": "version",
        "type": "uint8"
      }
    ],
    "name": "Initialized",
    "type": "event"
  },
  {
    "anonymous": false,
    "inputs": [
      {
        "indexed": false,
        "internalType": "address",
        "name": "position",
        "type": "address"
      }
    ],
    "name": "PositionCreated",
    "type": "event"
  },
  {
    "anonymous": false,
    "inputs": [
      {
        "indexed": true,
        "internalType": "bytes32",
        "name": "role",
        "type": "bytes32"
      },
      {
        "indexed": true,
        "internalType": "bytes32",
        "name": "previousAdminRole",
        "type": "bytes32"
      },
      {
        "indexed": true,
        "internalType": "bytes32",
        "name": "newAdminRole",
        "type": "bytes32"
      }
    ],
    "name": "RoleAdminChanged",
    "type": "event"
  },
  {
    "anonymous": false,
    "inputs": [
      {
        "indexed": true,
        "internalType": "bytes32",
        "name": "role",
        "type": "bytes32"
      },
      {
        "indexed": true,
        "internalType": "address",
        "name": "account",
        "type": "address"
      },
      {
        "indexed": true,
        "internalType": "address",
        "name": "sender",
        "type": "address"
      }
    ],
    "name": "RoleGranted",
    "type": "event"
  },
  {
    "anonymous": false,
    "inputs": [
      {
        "indexed": true,
        "internalType": "bytes32",
        "name": "role",
        "type": "bytes32"
      },
      {
        "indexed": true,
        "internalType": "address",
        "name": "account",
        "type": "address"
      },
      {
        "indexed": true,
        "internalType": "address",
        "name": "sender",
        "type": "address"
      }
    ],
    "name": "RoleRevoked",
    "type": "event"
  },
  {
    "inputs": [],
    "name": "BOOKKEEPER_ADDRESS",
    "outputs": [
      {
        "internalType": "address",
        "name": "",
        "type": "address"
      }
    ],
    "stateMutability": "view",
    "type": "function"
  },
  {
    "inputs": [],
    "name": "DEFAULT_ADMIN_ROLE",
    "outputs": [
      {
        "internalType": "bytes32",
        "name": "",
        "type": "bytes32"
      }
    ],
    "stateMutability": "view",
    "type": "function"
  },
  {
    "inputs": [],
    "name": "FACTORY_ADDRESS",
    "outputs": [
      {
        "internalType": "address",
        "name": "",
        "type": "address"
      }
    ],
    "stateMutability": "view",
    "type": "function"
  },
  {
    "inputs": [
      {
        "components": [
          {
            "internalType": "bytes3",
            "name": "standard",
            "type": "bytes3"
          },
          {
            "internalType": "address",
            "name": "addr",
            "type": "address"
          },
          {
            "internalType": "uint256",
            "name": "id",
            "type": "uint256"
          },
          {
            "internalType": "bytes",
            "name": "data",
            "type": "bytes"
          }
        ],
        "internalType": "struct Asset",
        "name": "",
        "type": "tuple"
      },
      {
        "internalType": "bytes",
        "name": "",
        "type": "bytes"
      }
    ],
    "name": "canHandleAsset",
    "outputs": [
      {
        "internalType": "bool",
        "name": "",
        "type": "bool"
      }
    ],
    "stateMutability": "pure",
    "type": "function"
  },
  {
    "inputs": [
      {
        "internalType": "address",
        "name": "sender",
        "type": "address"
      },
      {
        "components": [
          {
            "internalType": "uint256",
            "name": "loanAmount",
            "type": "uint256"
          },
          {
            "internalType": "uint256",
            "name": "collAmount",
            "type": "uint256"
          },
          {
            "components": [
              {
                "internalType": "bytes3",
                "name": "standard",
                "type": "bytes3"
              },
              {
                "internalType": "address",
                "name": "addr",
                "type": "address"
              },
              {
                "internalType": "uint256",
                "name": "id",
                "type": "uint256"
              },
              {
                "internalType": "bytes",
                "name": "data",
                "type": "bytes"
              }
            ],
            "internalType": "struct Asset",
            "name": "loanAsset",
            "type": "tuple"
          },
          {
            "components": [
              {
                "internalType": "bytes3",
                "name": "standard",
                "type": "bytes3"
              },
              {
                "internalType": "address",
                "name": "addr",
                "type": "address"
              },
              {
                "internalType": "uint256",
                "name": "id",
                "type": "uint256"
              },
              {
                "internalType": "bytes",
                "name": "data",
                "type": "bytes"
              }
            ],
            "internalType": "struct Asset",
            "name": "collAsset",
            "type": "tuple"
          },
          {
            "internalType": "uint256",
            "name": "minCollateralRatio",
            "type": "uint256"
          },
          {
            "internalType": "uint256",
            "name": "maxDuration",
            "type": "uint256"
          },
          {
            "components": [
              {
                "internalType": "address",
                "name": "addr",
                "type": "address"
              },
              {
                "internalType": "bytes",
                "name": "parameters",
                "type": "bytes"
              }
            ],
            "internalType": "struct ModuleReference",
            "name": "lenderAccount",
            "type": "tuple"
          },
          {
            "components": [
              {
                "internalType": "address",
                "name": "addr",
                "type": "address"
              },
              {
                "internalType": "bytes",
                "name": "parameters",
                "type": "bytes"
              }
            ],
            "internalType": "struct ModuleReference",
            "name": "borrowerAccount",
            "type": "tuple"
          },
          {
            "components": [
              {
                "internalType": "address",
                "name": "addr",
                "type": "address"
              },
              {
                "internalType": "bytes",
                "name": "parameters",
                "type": "bytes"
              }
            ],
            "internalType": "struct ModuleReference",
            "name": "assessor",
            "type": "tuple"
          },
          {
            "components": [
              {
                "internalType": "address",
                "name": "addr",
                "type": "address"
              },
              {
                "internalType": "bytes",
                "name": "parameters",
                "type": "bytes"
              }
            ],
            "internalType": "struct ModuleReference",
            "name": "liquidator",
            "type": "tuple"
          },
          {
            "components": [
              {
                "internalType": "address",
                "name": "addr",
                "type": "address"
              },
              {
                "internalType": "bytes",
                "name": "parameters",
                "type": "bytes"
              }
            ],
            "internalType": "struct ModuleReference",
            "name": "loanOracle",
            "type": "tuple"
          },
          {
            "components": [
              {
                "internalType": "address",
                "name": "addr",
                "type": "address"
              },
              {
                "internalType": "bytes",
                "name": "parameters",
                "type": "bytes"
              }
            ],
            "internalType": "struct ModuleReference",
            "name": "collateralOracle",
            "type": "tuple"
          },
          {
            "internalType": "address",
            "name": "factory",
            "type": "address"
          },
          {
            "components": [
              {
                "internalType": "address",
                "name": "addr",
                "type": "address"
              },
              {
                "internalType": "bytes",
                "name": "parameters",
                "type": "bytes"
              }
            ],
            "internalType": "struct ModuleReference",
            "name": "position",
            "type": "tuple"
          },
          {
            "internalType": "uint256",
            "name": "deploymentTime",
            "type": "uint256"
          }
        ],
        "internalType": "struct Agreement",
        "name": "agreement",
        "type": "tuple"
      },
      {
        "internalType": "bool",
        "name": "distribute",
        "type": "bool"
      },
      {
        "internalType": "bytes",
        "name": "parameters",
        "type": "bytes"
      }
    ],
    "name": "close",
    "outputs": [
      {
        "internalType": "uint256",
        "name": "",
        "type": "uint256"
      }
    ],
    "stateMutability": "nonpayable",
    "type": "function"
  },
  {
    "inputs": [],
    "name": "createPosition",
    "outputs": [
      {
        "internalType": "address",
        "name": "addr",
        "type": "address"
      }
    ],
    "stateMutability": "nonpayable",
    "type": "function"
  },
  {
    "inputs": [
      {
        "components": [
          {
            "internalType": "bytes3",
            "name": "standard",
            "type": "bytes3"
          },
          {
            "internalType": "address",
            "name": "addr",
            "type": "address"
          },
          {
            "internalType": "uint256",
            "name": "id",
            "type": "uint256"
          },
          {
            "internalType": "bytes",
            "name": "data",
            "type": "bytes"
          }
        ],
        "internalType": "struct Asset",
        "name": "asset",
        "type": "tuple"
      },
      {
        "internalType": "uint256",
        "name": "amount",
        "type": "uint256"
      },
      {
        "internalType": "bytes",
        "name": "parameters",
        "type": "bytes"
      }
    ],
    "name": "deploy",
    "outputs": [],
    "stateMutability": "nonpayable",
    "type": "function"
  },
  {
    "inputs": [
      {
        "internalType": "bytes",
        "name": "parameters",
        "type": "bytes"
      }
    ],
    "name": "getCloseAmount",
    "outputs": [
      {
        "internalType": "uint256",
        "name": "",
        "type": "uint256"
      }
    ],
    "stateMutability": "view",
    "type": "function"
  },
  {
    "inputs": [
      {
        "internalType": "bytes32",
        "name": "role",
        "type": "bytes32"
      }
    ],
    "name": "getRoleAdmin",
    "outputs": [
      {
        "internalType": "bytes32",
        "name": "",
        "type": "bytes32"
      }
    ],
    "stateMutability": "view",
    "type": "function"
  },
  {
    "inputs": [
      {
        "internalType": "bytes32",
        "name": "role",
        "type": "bytes32"
      },
      {
        "internalType": "address",
        "name": "account",
        "type": "address"
      }
    ],
    "name": "grantRole",
    "outputs": [],
    "stateMutability": "nonpayable",
    "type": "function"
  },
  {
    "inputs": [
      {
        "internalType": "bytes32",
        "name": "role",
        "type": "bytes32"
      },
      {
        "internalType": "address",
        "name": "account",
        "type": "address"
      }
    ],
    "name": "hasRole",
    "outputs": [
      {
        "internalType": "bool",
        "name": "",
        "type": "bool"
      }
    ],
    "stateMutability": "view",
    "type": "function"
  },
  {
    "inputs": [
      {
        "components": [
          {
            "internalType": "uint256",
            "name": "loanAmount",
            "type": "uint256"
          },
          {
            "internalType": "uint256",
            "name": "collAmount",
            "type": "uint256"
          },
          {
            "components": [
              {
                "internalType": "bytes3",
                "name": "standard",
                "type": "bytes3"
              },
              {
                "internalType": "address",
                "name": "addr",
                "type": "address"
              },
              {
                "internalType": "uint256",
                "name": "id",
                "type": "uint256"
              },
              {
                "internalType": "bytes",
                "name": "data",
                "type": "bytes"
              }
            ],
            "internalType": "struct Asset",
            "name": "loanAsset",
            "type": "tuple"
          },
          {
            "components": [
              {
                "internalType": "bytes3",
                "name": "standard",
                "type": "bytes3"
              },
              {
                "internalType": "address",
                "name": "addr",
                "type": "address"
              },
              {
                "internalType": "uint256",
                "name": "id",
                "type": "uint256"
              },
              {
                "internalType": "bytes",
                "name": "data",
                "type": "bytes"
              }
            ],
            "internalType": "struct Asset",
            "name": "collAsset",
            "type": "tuple"
          },
          {
            "internalType": "uint256",
            "name": "minCollateralRatio",
            "type": "uint256"
          },
          {
            "internalType": "uint256",
            "name": "maxDuration",
            "type": "uint256"
          },
          {
            "components": [
              {
                "internalType": "address",
                "name": "addr",
                "type": "address"
              },
              {
                "internalType": "bytes",
                "name": "parameters",
                "type": "bytes"
              }
            ],
            "internalType": "struct ModuleReference",
            "name": "lenderAccount",
            "type": "tuple"
          },
          {
            "components": [
              {
                "internalType": "address",
                "name": "addr",
                "type": "address"
              },
              {
                "internalType": "bytes",
                "name": "parameters",
                "type": "bytes"
              }
            ],
            "internalType": "struct ModuleReference",
            "name": "borrowerAccount",
            "type": "tuple"
          },
          {
            "components": [
              {
                "internalType": "address",
                "name": "addr",
                "type": "address"
              },
              {
                "internalType": "bytes",
                "name": "parameters",
                "type": "bytes"
              }
            ],
            "internalType": "struct ModuleReference",
            "name": "assessor",
            "type": "tuple"
          },
          {
            "components": [
              {
                "internalType": "address",
                "name": "addr",
                "type": "address"
              },
              {
                "internalType": "bytes",
                "name": "parameters",
                "type": "bytes"
              }
            ],
            "internalType": "struct ModuleReference",
            "name": "liquidator",
            "type": "tuple"
          },
          {
            "components": [
              {
                "internalType": "address",
                "name": "addr",
                "type": "address"
              },
              {
                "internalType": "bytes",
                "name": "parameters",
                "type": "bytes"
              }
            ],
            "internalType": "struct ModuleReference",
            "name": "loanOracle",
            "type": "tuple"
          },
          {
            "components": [
              {
                "internalType": "address",
                "name": "addr",
                "type": "address"
              },
              {
                "internalType": "bytes",
                "name": "parameters",
                "type": "bytes"
              }
            ],
            "internalType": "struct ModuleReference",
            "name": "collateralOracle",
            "type": "tuple"
          },
          {
            "internalType": "address",
            "name": "factory",
            "type": "address"
          },
          {
            "components": [
              {
                "internalType": "address",
                "name": "addr",
                "type": "address"
              },
              {
                "internalType": "bytes",
                "name": "parameters",
                "type": "bytes"
              }
            ],
            "internalType": "struct ModuleReference",
            "name": "position",
            "type": "tuple"
          },
          {
            "internalType": "uint256",
            "name": "deploymentTime",
            "type": "uint256"
          }
        ],
        "internalType": "struct Agreement",
        "name": "agreement",
        "type": "tuple"
      },
      {
        "internalType": "bytes",
        "name": "parameters",
        "type": "bytes"
      }
    ],
    "name": "initCheck",
    "outputs": [],
    "stateMutability": "view",
    "type": "function"
  },
  {
    "inputs": [],
    "name": "initialize",
    "outputs": [],
    "stateMutability": "nonpayable",
    "type": "function"
  },
  {
    "inputs": [
      {
        "internalType": "address payable",
        "name": "destination",
        "type": "address"
      },
      {
        "internalType": "bytes",
        "name": "data",
        "type": "bytes"
      },
      {
        "internalType": "bool",
        "name": "delegateCall",
        "type": "bool"
      }
    ],
    "name": "passThrough",
    "outputs": [
      {
        "internalType": "bool",
        "name": "",
        "type": "bool"
      },
      {
        "internalType": "bytes",
        "name": "",
        "type": "bytes"
      }
    ],
    "stateMutability": "payable",
    "type": "function"
  },
  {
    "inputs": [
      {
        "internalType": "bytes32",
        "name": "role",
        "type": "bytes32"
      },
      {
        "internalType": "address",
        "name": "account",
        "type": "address"
      }
    ],
    "name": "renounceRole",
    "outputs": [],
    "stateMutability": "nonpayable",
    "type": "function"
  },
  {
    "inputs": [
      {
        "internalType": "bytes32",
        "name": "role",
        "type": "bytes32"
      },
      {
        "internalType": "address",
        "name": "account",
        "type": "address"
      }
    ],
    "name": "revokeRole",
    "outputs": [],
    "stateMutability": "nonpayable",
    "type": "function"
  },
  {
    "inputs": [
      {
        "internalType": "bytes4",
        "name": "interfaceId",
        "type": "bytes4"
      }
    ],
    "name": "supportsInterface",
    "outputs": [
      {
        "internalType": "bool",
        "name": "",
        "type": "bool"
      }
    ],
    "stateMutability": "view",
    "type": "function"
  },
  {
    "inputs": [
      {
        "internalType": "address",
        "name": "controller",
        "type": "address"
      }
    ],
    "name": "transferContract",
    "outputs": [],
    "stateMutability": "nonpayable",
    "type": "function"
  },
  {
    "stateMutability": "payable",
    "type": "receive"
  }
]